taskiq_psqlpy/__init__.py
taskiq_psqlpy/exceptions.py
taskiq_psqlpy/queries.py
taskiq_psqlpy/result_backend.py
taskiq_psqlpy-0.1.7.dist-info/METADATA
taskiq_psqlpy-0.1.7.dist-info/WHEEL
taskiq_psqlpy-0.1.7.dist-info/RECORD
