Metadata-Version: 2.3
Name: taskiq-psqlpy
Version: 0.1.7
Summary: PSQLPy and PostgreSQL integration for taskiq
Keywords: taskiq,tasks,distributed,async,postgresql,result_backend,psqlpy
Author: taskiq-team
Author-email: taskiq@norely.com
Requires-Python: >=3.9.0,<4.0.0
Classifier: Programming Language :: Python
Classifier: Programming Language :: Python :: 3
Classifier: Programming Language :: Python :: 3.9
Classifier: Programming Language :: Python :: 3.10
Classifier: Programming Language :: Python :: 3.11
Classifier: Programming Language :: Python :: 3.12
Classifier: Programming Language :: Python :: 3.13
Classifier: Programming Language :: Python :: 3 :: Only
Requires-Dist: psqlpy (>=0.11.1,<0.12.0)
Requires-Dist: taskiq (>=0.11.17,<0.12.0)
Project-URL: Homepage, https://github.com/taskiq-python/taskiq-psqlpy
Project-URL: Repository, https://github.com/taskiq-python/taskiq-psqlpy
